geoip2datreverse
geoip2fastreverse
