Metadata-Version: 2.4
Name: geoip2fastreverse
Version: 0.0.1b3
Summary: GeoIP2FastReverse - You provide a country/ASN/city code and we return the corresponding IPv4/IPv6 networks. Useful for firewall rules. Uses the Maxmind Geolite2 database updated twice a week. Fast as always, and in pure Python!
Home-page: https://github.com/rabuchaim/geoip2fastreverse
Author: Ricardo Abuchaim
Author-email: ricardoabuchaim@gmail.com
Maintainer: Ricardo Abuchaim
Maintainer-email: ricardoabuchaim@gmail.com
License: MIT
Project-URL: Issue Tracker, https://github.com/rabuchaim/geoip2fastreverse/issues
Project-URL: Source code, https://github.com/rabuchaim/geoip2fastreverse
Project-URL: Latest DAT files, https://github.com/rabuchaim/geoip2fastreverse/releases/latest
Project-URL: Legacy v1.1.X DAT files, https://github.com/rabuchaim/geoip2fastreverse/releases/tag/LEGACY
Project-URL: Discussion Group, https://groups.google.com/g/geoip2fastreverse
Keywords: geoipreverse,reverse,geoip,geoip2,geolite2,maxmind,geoip2fast,geolocation,geolocalization,geo ip,ipaddress,ip,geo,ipv4,ipv6,pure-python,purepython,pure python,geoiptofast,geoiptoofast,geoip2dat,mmdb,tools
Classifier: Development Status :: 5 - Production/Stable
Classifier: Topic :: Security
Classifier: Topic :: Internet
Classifier: Topic :: Internet :: Finger
Classifier: Topic :: Scientific/Engineering
Classifier: Topic :: System :: Monitoring
Classifier: Topic :: System :: Networking
Classifier: Topic :: System :: Systems Administration
Classifier: Topic :: Software Development :: Libraries
Classifier: Topic :: Software Development :: Libraries :: Python Modules
Classifier: Topic :: Software Development :: Localization
Classifier: Topic :: Utilities
Classifier: Intended Audience :: Developers
Classifier: Intended Audience :: Information Technology
Classifier: Intended Audience :: System Administrators
Classifier: Operating System :: MacOS
Classifier: Operating System :: Microsoft :: Windows :: Windows 10
Classifier: Operating System :: Microsoft :: Windows :: Windows 11
Classifier: Operating System :: Unix
Classifier: Operating System :: POSIX
Classifier: Operating System :: POSIX :: Linux
Classifier: Operating System :: POSIX :: BSD
Classifier: Operating System :: POSIX :: BSD :: FreeBSD
Classifier: Programming Language :: Python
Classifier: Programming Language :: Python :: 3.10
Classifier: Programming Language :: Python :: 3.11
Classifier: Programming Language :: Python :: 3.12
Classifier: Programming Language :: Python :: 3.13
Classifier: Programming Language :: Python :: 3.14
Classifier: Programming Language :: Python :: Implementation :: PyPy
Classifier: License :: OSI Approved :: MIT License
Requires-Python: >=3.10
License-File: LICENSE
Dynamic: author
Dynamic: author-email
Dynamic: classifier
Dynamic: description
Dynamic: description-content-type
Dynamic: home-page
Dynamic: keywords
Dynamic: license
Dynamic: license-file
Dynamic: maintainer
Dynamic: maintainer-email
Dynamic: project-url
Dynamic: requires-python
Dynamic: summary
